datasette_plugin_template_demo/__init__.py
datasette_plugin_template_demo-0.1.dist-info/METADATA
datasette_plugin_template_demo-0.1.dist-info/WHEEL
datasette_plugin_template_demo-0.1.dist-info/entry_points.txt
datasette_plugin_template_demo-0.1.dist-info/top_level.txt
datasette_plugin_template_demo-0.1.dist-info/RECORD
