Metadata-Version: 2.1
Name: datasette-plugin-template-demo
Version: 0.1
Summary: Demonstrating https://github.com/simonw/datasette-plugin
Home-page: https://github.com/simonw/datasette-plugin-template-demo
Author: Simon Willison
License: Apache License, Version 2.0
Project-URL: Issues, https://gitlab.com/simonw/datasette-plugin-template-demo/issues
Project-URL: CI, https://github.com/simonw/datasette-plugin-template-demo/actions
Project-URL: Changelog, https://github.com/simonw/datasette-plugin-template-demo/releases
Platform: UNKNOWN
Requires-Dist: datasette
Provides-Extra: test
Requires-Dist: pytest ; extra == 'test'
Requires-Dist: pytest-asyncio ; extra == 'test'
Requires-Dist: httpx ; extra == 'test'
